picklebase/__init__.py
picklebase/__eval/__init__.py
picklebase/base/__init__.py
picklebase/base/file/__init__.py
picklebase/chart/__init__.py
picklebase/chart/boxplot/__init__.py
picklebase/chart/boxplot/outlier.py
picklebase/chart/correlation/__init__.py
picklebase/chart/cumulative_gain/__init__.py
picklebase/chart/density/__init__.py
picklebase/chart/histogram/__init__.py
picklebase/chart/lift/__init__.py
picklebase/chart/pairplot/__init__.py
picklebase/chart/precision_recall/__init__.py
picklebase/chart/roc/__init__.py
picklebase/chart/scatterplot/__init__.py
picklebase/data/__init__.py
picklebase/data/column/__init__.py
picklebase/data/create/__init__.py
picklebase/data/load/__init__.py
picklebase/data/null/__init__.py
picklebase/data/row/__index.py
picklebase/data/row/__init__.py
picklebase/data/row/__value.py
picklebase/data/save/__init__.py
picklebase/data/series/__init__.py
picklebase/data/stat/__init__.py
picklebase/data/value/__init__.py
picklebase/dlearn/__init__.py
picklebase/dlearn/classification/__init__.py
picklebase/mlearn/__init__.py
picklebase/mlearn/data.py
picklebase/mlearn/association/__init__.py
picklebase/mlearn/association/apriori/__init__.py
picklebase/mlearn/classification/__init__.py
picklebase/mlearn/classification/__base/__init__.py
picklebase/mlearn/classification/dectree/__init__.py
picklebase/mlearn/classification/gradboost/__init__.py
picklebase/mlearn/classification/knn/__init__.py
picklebase/mlearn/classification/logreg/__init__.py
picklebase/mlearn/classification/rndforest/__init__.py
picklebase/mlearn/classification/svm/__init__.py
picklebase/mlearn/classification/x-bagging/__init__.py
picklebase/mlearn/classification/x-gradboost_bag/__init__.py
picklebase/mlearn/classification/x-gradboost_cv/__init__.py
picklebase/mlearn/classification/x-logreg_cv/__init__.py
picklebase/mlearn/classification/x-randforest_cv/__init__.py
picklebase/mlearn/classification/x_dectree_cv/__init__.py
picklebase/mlearn/clustering/__init__.py
picklebase-0.0.2.dist-info/LICENSE.txt
picklebase-0.0.2.dist-info/METADATA
picklebase-0.0.2.dist-info/WHEEL
picklebase-0.0.2.dist-info/top_level.txt
picklebase-0.0.2.dist-info/RECORD
