Metadata-Version: 2.1
Name: picklebase
Version: 0.0.2
Summary: a Python Package
Home-page: https://github.com/ah4d1/picklebase
Author: Ahadi Aprianto
Author-email: relations@aprian.my.id
Project-URL: Bug Tracker, https://github.com/ah4d1/picklebase
Classifier: Programming Language :: Python :: 3
Classifier: License :: OSI Approved :: BSD License
Classifier: Operating System :: OS Independent
Requires-Python: >=3.6
License-File: LICENSE.txt
Requires-Dist: imblearn >=0.0
Requires-Dist: imbalanced-learn >=0.8.0
Requires-Dist: matplotlib >=3.3.1
Requires-Dist: numpy >=1.19.1
Requires-Dist: seaborn >=0.11.1
Requires-Dist: scikit-learn >=0.24.2
Requires-Dist: scikit-plot >=0.3.7
Requires-Dist: statsmodels >=0.12.2
Requires-Dist: scipy ==1.11.4
Requires-Dist: pyodbc >=5.1.0
Requires-Dist: twint >=2.1.20
Requires-Dist: keras >=3.3.3
Requires-Dist: tensorflow >=2.16.1
Requires-Dist: mlxtend >=0.23.1
Requires-Dist: kneed >=0.8.5
